LICENSE
MANIFEST.in
README.md
setup.cfg
setup.py
pyjo_mongo/__init__.py
pyjo_mongo/document.py
pyjo_mongo/queryset.py
pyjo_mongo.egg-info/PKG-INFO
pyjo_mongo.egg-info/SOURCES.txt
pyjo_mongo.egg-info/dependency_links.txt
pyjo_mongo.egg-info/requires.txt
pyjo_mongo.egg-info/top_level.txt
tests/__init__.py
tests/conftest.py
tests/test_core.py