Metadata-Version: 1.1
Name: pyjo-mongo
Version: 0.6.0
Summary: Pyjo for MongoDB
Home-page: https://github.com/marcopaz/pyjo_mongo
Author: Marco Pazzaglia
Author-email: marco@pazzaglia.me
License: UNKNOWN
Download-URL: https://github.com/marcopaz/pyjo_mongo/archive/0.6.0.tar.gz
Platform: UNKNOWN
